pycallgraph/__init__.py
pycallgraph/color.py
pycallgraph/config.py
pycallgraph/conftest.py
pycallgraph/decorators.py
pycallgraph/exceptions.py
pycallgraph/globbing_filter.py
pycallgraph/grouper.py
pycallgraph/metadata.py
pycallgraph/output/__init__.py
pycallgraph/output/calls.py
pycallgraph/output/gephi.py
pycallgraph/output/graphviz.py
pycallgraph/output/output.py
pycallgraph/output/pickle.py
pycallgraph/output/test/__init__.py
pycallgraph/output/test/test_gephi.py
pycallgraph/output/test/test_graphviz.py
pycallgraph/output/test/test_output.py
pycallgraph/output/ubigraph.py
pycallgraph/pycallgraph.py
pycallgraph/test/__init__.py
pycallgraph/test/calls.py
pycallgraph/test/test_color.py
pycallgraph/test/test_config.py
pycallgraph/test/test_decorators.py
pycallgraph/test/test_pycallgraph.py
pycallgraph/test/test_script.py
pycallgraph/test/test_trace_processor.py
pycallgraph/test/test_util.py
pycallgraph/tracer.py
pycallgraph/util.py
callgraph4py-2.0.0.dist-info/LICENSE
callgraph4py-2.0.0.dist-info/WHEEL
callgraph4py-2.0.0.dist-info/METADATA
callgraph4py-2.0.0.dist-info/RECORD
