Metadata-Version: 2.1
Name: callgraph4py
Version: 2.0.0
Summary: Create a Call Graph
Author: Essi Alizadeh
Author-email: pycallgraph@ealizadeh.com
Requires-Python: >=3.6.1,<4.0.0
Classifier: Programming Language :: Python :: 3
Classifier: Programming Language :: Python :: 3.7
Classifier: Programming Language :: Python :: 3.8
Classifier: Programming Language :: Python :: 3.9
Classifier: Topic :: Software Development :: Build Tools
Classifier: Topic :: Software Development :: Libraries :: Python Modules
Requires-Dist: memory_profiler (>=0.58.0,<0.59.0)
Requires-Dist: psutil (>=5.8.0,<6.0.0)
Requires-Dist: requests (>=2.25.1,<3.0.0)
